Metadata-Version: 2.1
Name: sql_metadata
Version: 2.14.0
Summary: Uses tokenized query returned by python-sqlparse and generates query metadata
Home-page: https://github.com/macbre/sql-metadata
License: MIT
Author: Maciej Brencz
Author-email: maciej.brencz@gmail.com
Requires-Python: >=3.8,<4.0
Classifier: License :: OSI Approved :: MIT License
Classifier: Programming Language :: Python :: 3
Classifier: Programming Language :: Python :: 3.8
Classifier: Programming Language :: Python :: 3.9
Classifier: Programming Language :: Python :: 3.10
Classifier: Programming Language :: Python :: 3.11
Classifier: Programming Language :: Python :: 3.12
Classifier: Programming Language :: Python :: 3.13
Requires-Dist: sqlparse (>=0.4.1,<0.6.0)
Project-URL: Repository, https://github.com/macbre/sql-metadata
